{
  "enabled": true,
  "title": "",
  "remark": "",
  "createTime": "2024-01-20T09:36:05.750272522Z",
  "updateTime": "2024-01-20T09:36:38.160473806Z",
  "deleteTime": "",
  "path": "n05aggregation/group/groupHaving",
  "engine": 0,
  "hooksConfiguration": null,
  "rateLimit": null,
  "configCustomized": false,
  "cacheConfig": {
    "enabled": false,
    "maxAge": 120,
    "public": false,
    "staleWhileRevalidate": 30
  },
  "liveQueryConfig": {
    "enabled": false,
    "pollingIntervalSeconds": 10
  },
  "authenticationConfig": null
}